snapvc/__init__.py
snapvc/housing.py
snapvc/ignore.py
snapvc/main.py
snapvc/revert.py
snapvc/snapshot.py
snapvc/staging.py
snapvc/utils.py
snapvc-1.2.1.dist-info/licenses/LICENSE
snapvc-1.2.1.dist-info/METADATA
snapvc-1.2.1.dist-info/WHEEL
snapvc-1.2.1.dist-info/entry_points.txt
snapvc-1.2.1.dist-info/top_level.txt
snapvc-1.2.1.dist-info/RECORD
