Metadata-Version: 2.4
Name: snapvc
Version: 1.2.1
Summary: A lightweight version control system with cross-platform support
Home-page: https://github.com/ShreyashM17/SnapVC
Author: Shreyash Mogaveera
Author-email: shreyashmogaveera@gmail.com
License: MIT
Project-URL: Bug Tracker, https://github.com/ShreyashM17/SnapVC/issues
Project-URL: Documentation, https://github.com/ShreyashM17/SnapVC#readme
Project-URL: Source Code, https://github.com/ShreyashM17/SnapVC
Keywords: version-control,vcs,educational,git,snapshots,cross-platform,cli,learning,development-tools
Classifier: Intended Audience :: Developers
Classifier: Intended Audience :: Education
Classifier: Topic :: Software Development :: Version Control
Classifier: Programming Language :: Python :: 3
Classifier: Programming Language :: Python :: 3.7
Classifier: Programming Language :: Python :: 3.8
Classifier: Programming Language :: Python :: 3.9
Classifier: Programming Language :: Python :: 3.10
Classifier: Programming Language :: Python :: 3.11
Classifier: Programming Language :: Python :: 3.12
Classifier: Operating System :: OS Independent
Classifier: Environment :: Console
Requires-Python: >=3.7
License-File: LICENSE
Dynamic: author
Dynamic: author-email
Dynamic: classifier
Dynamic: description
Dynamic: description-content-type
Dynamic: home-page
Dynamic: keywords
Dynamic: license
Dynamic: license-file
Dynamic: project-url
Dynamic: requires-python
Dynamic: summary
